fibsem/__init__.py
fibsem/acquire.py
fibsem/alignment.py
fibsem/calibration.py
fibsem/config.py
fibsem/configuration.py
fibsem/constants.py
fibsem/conversions.py
fibsem/gis.py
fibsem/microscope.py
fibsem/movement.py
fibsem/structures.py
fibsem/utils.py
fibsem/validation.py
fibsem/chat/.gitignore
fibsem/chat/main.py
fibsem/chat/requirements.txt
fibsem/config/deposition.dbp
fibsem/config/microscope-configuration.yaml
fibsem/config/odemis-configuration.yaml
fibsem/config/positions.yaml
fibsem/config/protocol.yaml
fibsem/config/tescan_manipulator.yaml
fibsem/config/tfs-aquilos2-configuration.yaml
fibsem/config/tfs-arctis-configuration.yaml
fibsem/config/tfs-hydra-configuration.yaml
fibsem/db/app.py
fibsem/db/config.yaml
fibsem/db/notebook.ipynb
fibsem/db/util.py
fibsem/db/v2/app.py
fibsem/db/v2/models.py
fibsem/db/v2/notebook.ipynb
fibsem/db/v2/util.py
fibsem/db/v3/app.py
fibsem/db/v3/models.py
fibsem/db/v3/notebook.ipynb
fibsem/db/v3/util.py
fibsem/detection/__init__.py
fibsem/detection/config-autolamella-liftout-hf-mega.yaml
fibsem/detection/config-autolamella-liftout.yaml
fibsem/detection/config-autolamella-serial-liftout-hf-mega.yaml
fibsem/detection/config-autolamella-serial-liftout.yaml
fibsem/detection/config-autolamella-waffle-v2-hf-mega.yaml
fibsem/detection/config-autolamella-waffle-v2.yaml
fibsem/detection/config-autolamella-waffle.yml
fibsem/detection/config-autoliftout-dm-embryo.yml
fibsem/detection/detection.py
fibsem/detection/evaluation.py
fibsem/detection/run_evaluation.py
fibsem/detection/test_image.tif
fibsem/detection/test_image_2.tif
fibsem/detection/utils.py
fibsem/detection/test_images/test_needle_mask.tif
fibsem/detection/test_images/test_needle_mask2.tif
fibsem/detection/test_images/test_needle_mask3.tif
fibsem/detection/test_images/serial/serial_liftout_mask_00.tif
fibsem/detection/test_images/serial/serial_liftout_mask_01.tif
fibsem/detection/test_images/serial/serial_liftout_mask_02.tif
fibsem-0.4.0.dist-info/licenses/LICENSE
fibsem-0.4.0.dist-info/METADATA
fibsem-0.4.0.dist-info/WHEEL
fibsem-0.4.0.dist-info/entry_points.txt
fibsem-0.4.0.dist-info/top_level.txt
fibsem-0.4.0.dist-info/RECORD
