Metadata-Version: 2.4
Name: fibsem
Version: 0.4.0
Summary: a universal api for fibsem control
Author-email: Patrick Cleeve <patrick@openfibsem.org>
License: MIT License
Project-URL: Homepage, https://github.com/DeMarcoLab/fibsem
Project-URL: Bug Tracker, https://github.com/DeMarcoLab/fibsem/issues
Classifier: Programming Language :: Python :: 3.8
Classifier: License :: OSI Approved :: MIT License
Classifier: Operating System :: OS Independent
Classifier: Framework :: napari
Requires-Python: >=3.8
License-File: LICENSE
Requires-Dist: tifffile>=2021.7.2
Requires-Dist: numpy<=2.0.0,>=1.23.5
Requires-Dist: scipy>=1.10.0
Requires-Dist: opencv-python-headless>=4.7.0.72
Requires-Dist: scikit-image>=0.19.3
Requires-Dist: matplotlib>=3.7.0
Requires-Dist: tqdm>=4.65.0
Requires-Dist: pytest>=7.2.2
Requires-Dist: petname>=2.6
Requires-Dist: pandas>=2.0.0
Requires-Dist: pyyaml>=6.0
Requires-Dist: psygnal
Provides-Extra: ml
Requires-Dist: zarr>=2.13.6; extra == "ml"
Requires-Dist: dask>=2023.3.0; extra == "ml"
Requires-Dist: torch<=2.1.2,>=2.0.0; extra == "ml"
Requires-Dist: torchvision>=0.15.1; extra == "ml"
Requires-Dist: segmentation-models-pytorch>=0.3.2; extra == "ml"
Requires-Dist: plotly>=5.14.1; extra == "ml"
Requires-Dist: kaleido==0.2.0; extra == "ml"
Requires-Dist: transformers>=4.36.2; extra == "ml"
Provides-Extra: ui
Requires-Dist: napari<=0.5.3,>=0.4.17; extra == "ui"
Requires-Dist: pyqt5>=5.15.9; extra == "ui"
Requires-Dist: matplotlib_scalebar>=0.8.1; extra == "ui"
Provides-Extra: odemis
Requires-Dist: pylibtiff; extra == "odemis"
Provides-Extra: reporting
Requires-Dist: plotly>=5.14.1; extra == "reporting"
Requires-Dist: reportlab; extra == "reporting"
Dynamic: license-file
